{
    "v2": "1.2.6",
    "versions": [
        "1.1"
    ],
    "posts": [
        {
            "date": "2 novembre 2021",
            "title": "Merci d’avoir participé à la Zone Safari Pokémon GO de Philadelphie !",
            "link": "https://pokemongolive.com/fr/post/philadelphia-safari-zone-2021/"
        },
        {
            "date": "1 novembre 2021",
            "title": "Dedenne fait une entrée éblouissante lors de la Fête des Lumières, mais avec la lumière viennent les ténèbres...",
            "link": "https://pokemongolive.com/fr/post/festival-of-lights-2021/"
        },
        {
            "date": "25 octobre 2021",
            "title": "Célébrez le Día de Muertos dans Pokémon GO !",
            "link": "https://pokemongolive.com/fr/post/diademuertos2021/"
        },
        {
            "date": "22 octobre 2021",
            "title": "À venir en novembre : Fête des lumières et plus encore !",
            "link": "https://pokemongolive.com/fr/post/nov-2021-events/"
        },
        {
            "date": "22 octobre 2021",
            "title": "Journée Communauté de novembre : Lixy, le Pokémon Flash, sera à l’honneur !",
            "link": "https://pokemongolive.com/fr/post/communityday-nov21/"
        },
        {
            "date": "21 octobre 2021",
            "title": "Journal des développeurs : Journée communautaire",
            "link": "https://pokemongolive.com/fr/post/devdiary-10192021/"
        },
        {
            "date": "20 octobre 2021",
            "title": "Votre ascension vers les Championnats du monde Pokémon 2022",
            "link": "https://pokemongolive.com/fr/post/pgo-championship-announce-details/"
        },
        {
            "date": "13 octobre 2021",
            "title": "À venir : des tests visant à améliorer l’expérience Pokémon GO",
            "link": "https://pokemongolive.com/fr/post/ux-testing-2021/"
        },
        {
            "date": "11 octobre 2021",
            "title": "Pokémon GO Halloween débarque avec des Compagnons Cauchemar\net des Copains Effrayants ! Un bonbon ou un sort ? Pourquoi pas les deux ?",
            "link": "https://pokemongolive.com/fr/post/halloween-2021/"
        },
        {
            "date": "5 octobre 2021",
            "title": "Annonce de la série de championnats Pokémon GO",
            "link": "https://pokemongolive.com/fr/post/pgo-championship-series-announce/"
        },
        {
            "date": "24 septembre 2021",
            "title": "À venir en octobre : Pokémon GO Halloween 2021 et bien plus encore !",
            "link": "https://pokemongolive.com/fr/post/oct-2021-events/"
        },
        {
            "date": "21 septembre 2021",
            "title": "Zarude, le Pokémon fabuleux, fait son entrée dans Pokémon GO pour fêter la sortie mondiale de Pokémon, le film : Les secrets de la jungle",
            "link": "https://pokemongolive.com/fr/post/movie-2021/"
        },
        {
            "date": "16 septembre 2021",
            "title": "La vidéo du 5e anniversaire de Pokémon GO est là !",
            "link": "https://pokemongolive.com/fr/post/birthday2021-video/"
        },
        {
            "date": "13 septembre 2021",
            "title": "Couafarel et les Pokémon costumés sont les stars de la Fashion Week dans Pokémon GO !",
            "link": "https://pokemongolive.com/fr/post/fashion-week-2021/"
        },
        {
            "date": "9 septembre 2021",
            "title": "Journée Communauté d'octobre : Skelénox, le Pokémon Requiem, sera à l'honneur !",
            "link": "https://pokemongolive.com/fr/post/communityday-oct21/"
        },
        {
            "date": "2 septembre 2021",
            "title": "De nouvelles dates et de nouveaux détails sont désormais disponibles pour l'évènement Zone Safari qui avait été reporté dans Pokémon GO",
            "link": "https://pokemongolive.com/fr/post/safarizone-2021/"
        },
        {
            "date": "1 septembre 2021",
            "title": "Sepiatop et Sepiatroce font leur entrée dans Pokémon GO pendant l'événement Fantasmagorie Psy !",
            "link": "https://pokemongolive.com/fr/post/psychic-spectacular-2021/"
        },
        {
            "date": "1 septembre 2021",
            "title": "Mise au point de notre groupe de travail",
            "link": "https://pokemongolive.com/fr/post/sep-taskforce-update/"
        },
        {
            "date": "27 août 2021",
            "title": "En septembre débarque la Saison Chenapan et plus encore ! Préparez-vous !",
            "link": "https://pokemongolive.com/fr/post/sept-2021-events/"
        },
        {
            "date": "27 août 2021",
            "title": "Bienvenue à la Saison Chenapan !",
            "link": "https://pokemongolive.com/fr/post/season-of-mischief-2021/"
        }
    ]
}