{
    "versions": [
        "1.1"
    ],
    "posts": [
        {
            "date": "February 24, 2021",
            "title": "A new Season is coming—and so are March’s Pokémon GO events!",
            "link": "https://pokemongolive.com/en/post/mar-2021-events/"
        },
        {
            "date": "February 22, 2021",
            "title": "GO Battle League Season 7 begins Monday, March 1, 2021, at 1:00 p.m. PST (GMT −8)",
            "link": "https://pokemongolive.com/en/post/gobattleleague-season7/"
        },
        {
            "date": "February 22, 2021",
            "title": "The Season of Legends starts soon!",
            "link": "https://pokemongolive.com/en/post/season-of-legends-2021/"
        },
        {
            "date": "February 19, 2021",
            "title": "Everything you need to know before Pokémon GO Tour: Kanto!",
            "link": "https://pokemongolive.com/en/post/pokemongotour-kanto-knowbeforeyougo/"
        },
        {
            "date": "February 18, 2021",
            "title": "Close out the Pokémon Day weekend with a Kanto-themed Raid Day!",
            "link": "https://pokemongolive.com/en/post/kanto-raid-day-2021/"
        },
        {
            "date": "February 16, 2021",
            "title": "March Community Day’s featured Pokémon will be Fletchling!",
            "link": "https://pokemongolive.com/en/post/communityday-mar21/"
        },
        {
            "date": "February 11, 2021",
            "title": "Keep the Kanto celebration going after Pokémon GO Tour: Kanto with a special event!",
            "link": "https://pokemongolive.com/en/post/kanto-celebration-event-2021/"
        },
        {
            "date": "February 10, 2021",
            "title": "Pokémon GO Tour: Kanto sweepstakes",
            "link": "https://pokemongolive.com/en/post/pokemongotour-kanto-sweepstakes/"
        },
        {
            "date": "February 9, 2021",
            "title": "Celebrate Pokémon’s anniversary with a brand-new event—Pokémon GO Tour: Kanto!",
            "link": "https://pokemongolive.com/en/post/pokemongotour-kanto/"
        },
        {
            "date": "February 9, 2021",
            "title": "Are you ready for Pokémon GO Tour: Kanto? Learn more about what to expect from the event!",
            "link": "https://pokemongolive.com/en/post/pokemongotour-kanto-details/"
        },
        {
            "date": "February 8, 2021",
            "title": "Pokémon GO Valentine’s Day celebration 2021",
            "link": "https://pokemongolive.com/en/post/valentinesday2021/"
        },
        {
            "date": "February 2, 2021",
            "title": "Feel the love with Pokémon GO’s February events!",
            "link": "https://pokemongolive.com/en/post/feb-2021-events/"
        },
        {
            "date": "February 2, 2021",
            "title": "Celebrate Lunar New Year with Pokémon GO!",
            "link": "https://pokemongolive.com/en/post/lunar-2021/"
        },
        {
            "date": "February 2, 2021",
            "title": "Which journey will you choose? Pokémon GO Tour: Kanto ticket holders will be able to choose their event version soon!",
            "link": "https://pokemongolive.com/en/post/pokemongotour-kanto-version/"
        },
        {
            "date": "January 27, 2021",
            "title": "Team GO Rocket is celebrating? Smells like trouble!",
            "link": "https://pokemongolive.com/en/post/team-go-rocket-celebration-2021/"
        },
        {
            "date": "January 25, 2021",
            "title": "GO Battle League Season 6 begins Monday, November 30, 2020, at 1:00 p.m. PST (GMT −8)",
            "link": "https://pokemongolive.com/en/post/gobattleleague-season6/"
        },
        {
            "date": "January 25, 2021",
            "title": "Nothing to sneeze at—get ready for Limited Research featuring Sneasel! Plus, new Timed Research is coming soon!",
            "link": "https://pokemongolive.com/en/post/limited-research-sneasel-challenge/"
        },
        {
            "date": "January 19, 2021",
            "title": "Mega Ampharos is coming! Plus, get ready for an Incense Day featuring Mareep!",
            "link": "https://pokemongolive.com/en/post/incenseday-electric-dragon-mareep/"
        },
        {
            "date": "January 19, 2021",
            "title": "Countdown to Pokémon GO Tour: Kanto—celebrate the Johto region with us!",
            "link": "https://pokemongolive.com/en/post/johto-celebration-event-2021/"
        },
        {
            "date": "January 14, 2021",
            "title": "Rising to the challenge of January Community Day is none other than Machop!",
            "link": "https://pokemongolive.com/en/post/communityday-jan21/"
        }
    ]
}