{
    "versions": [
        "1.1"
    ],
    "posts": [
        {
            "date": "7/9/20",
            "title": "Team GO Rocket has taken over the GO Fest Weekly Challenge!",
            "link": "https://pokemongolive.com/en/post/gofestweeklychallenge-teamgorocket/"
        },
        {
            "date": "7/9/20",
            "title": "Battle Jessie and James by finding their Meowth balloon!",
            "link": "https://pokemongolive.com/en/post/teamgorocket-jessie-james/"
        },
        {
            "date": "7/7/20",
            "title": "Look up, Trainers—Team GO Rocket balloons have arrived in Pokémon GO!",
            "link": "https://pokemongolive.com/en/post/teamgorocket-balloon-launch/"
        },
        {
            "date": "7/6/20",
            "title": "Look closer to discover what Pokémon GO Fest 2020 has in store!",
            "link": "https://pokemongolive.com/en/post/pokemongofest2020-lookcloser/"
        },
        {
            "date": "7/3/20",
            "title": "Willow Report: Strange Scraps",
            "link": "https://pokemongolive.com/en/post/willowreport-strangescraps/"
        },
        {
            "date": "7/2/20",
            "title": "The featured Pokémon for July Community Day is Gastly!",
            "link": "https://pokemongolive.com/en/post/communityday-july20/"
        },
        {
            "date": "6/30/20",
            "title": "Kyurem arrives in five-star raids and more in July!",
            "link": "https://pokemongolive.com/en/post/jul2020-events/"
        },
        {
            "date": "6/25/20",
            "title": "Celebrate Pokémon GO’s fourth anniversary by completing weekly challenges to unlock more species of Pokémon that’ll appear during Pokémon GO Fest 2020!",
            "link": "https://pokemongolive.com/en/post/anniversary-gofest-weeklychallenges-2020/"
        },
        {
            "date": "6/24/20",
            "title": "Updates to events: Pinsir Raid Day",
            "link": "https://pokemongolive.com/en/post/pinsirraidday-update/"
        },
        {
            "date": "6/18/20",
            "title": "Limited tests incoming: daily guaranteed Pokémon encounters and Daily Free Boxes in the shop",
            "link": "https://pokemongolive.com/en/post/daily-encounter-daily-box/"
        },
        {
            "date": "6/17/20",
            "title": "Galarian Farfetch’d and new avatar items arrive in celebration of The Isle of Armor!",
            "link": "https://pokemongolive.com/en/post/pokemonpresents2020/"
        },
        {
            "date": "6/15/20",
            "title": "Nominate businesses for the Niantic Local Business Recovery Initiative ",
            "link": "https://pokemongolive.com/en/post/niantic-local-business-recovery-initiative/"
        },
        {
            "date": "6/15/20",
            "title": "Pokémon GO Fest 2020 brings summer adventure to you!",
            "link": "https://pokemongolive.com/en/post/pokemongofest2020-details/"
        },
        {
            "date": "6/12/20",
            "title": "Solstice-themed event and Bug Out! event details",
            "link": "https://pokemongolive.com/en/post/bugout-solstice-2020/"
        },
        {
            "date": "6/9/20",
            "title": "Pokémon GO to discontinue support on 32-bit Android devices",
            "link": "https://pokemongolive.com/en/post/32-bit-android-discontinued-support/"
        },
        {
            "date": "6/9/20",
            "title": "The featured Pokémon for June Community Day is Weedle!",
            "link": "https://pokemongolive.com/en/post/communityday-jun2020/"
        },
        {
            "date": "6/5/20",
            "title": "Certain Pokémon’s Alolan and Galarian forms will soon hatch from 7 km Eggs!",
            "link": "https://pokemongolive.com/en/post/7kmeggs-alolan-galarian-forms/"
        },
        {
            "date": "6/5/20",
            "title": "Latias and Latios zip back for another Special Raid Weekend event!",
            "link": "https://pokemongolive.com/en/post/weekendraid2020-latias-latios-2/"
        },
        {
            "date": "6/2/20",
            "title": "Feature updates: Adding stickers to Gifts coming soon; inviting friends to raids coming later this month!",
            "link": "https://pokemongolive.com/en/post/raid-gift-update-2020/"
        },
        {
            "date": "5/29/20",
            "title": "Zekrom’s Pokémon GO debut and more in June!",
            "link": "https://pokemongolive.com/en/post/jun2020-events/"
        }
    ]
}