{
    "v2": "1.2.8",
    "versions": [
        "1.1"
    ],
    "posts": [
        {
            "title": "8月の最新情報：「Pokémon GO Fest: Sapporo」と「Pokémon GO Fest 2022: フィナーレ」、「ザシアン」と「ザマゼンタ」がレイドバトルに再登場、「むしタイプポケモンのイベント」など！",
            "link": "https://pokemongolive.com/ja/post/august-2022-content-update/",
            "date": "2022年7月26日"
        },
        {
            "title": "「Pokémon GO Fest 2022: Seattle」にご参加いただき、ありがとうございました！",
            "link": "https://pokemongolive.com/ja/post/gofest-seattle-recap/",
            "date": "2022年7月26日"
        },
        {
            "title": "「おさんぽおこう」が『Pokémon GO』に新登場！",
            "link": "https://pokemongolive.com/ja/post/daily-adventure-incense-update/",
            "date": "2022年7月25日"
        },
        {
            "title": "「ヒスイイベント」で時代をさかのぼりましょう！",
            "link": "https://pokemongolive.com/ja/post/hisuian-discoveries/",
            "date": "2022年7月24日"
        },
        {
            "title": "『Pokémon GO』スペシャルドローンショーが「おたる潮まつり」にて実施決定！ライブ配信も！",
            "link": "https://pokemongolive.com/ja/post/droneshow-otaru/",
            "date": "2022年7月21日"
        },
        {
            "title": "「Pokémon GO Fest 2022: Seattle」の「グローバルチャレンジ」と「ウルトラアンロック」についてお知らせします！",
            "link": "https://pokemongolive.com/ja/post/gofest2022-seattle-ultraunlockchallenge/",
            "date": "2022年7月20日"
        },
        {
            "title": "2022年8月の「コミュニティ・デイ」：「ジグザグマ（ガラルのすがた）」",
            "link": "https://pokemongolive.com/ja/post/communityday-august-2022-galarian-zigzagoon/",
            "date": "2022年7月19日"
        },
        {
            "title": "ディベロッパーダイアリー：『Campfire』登場！",
            "link": "https://pokemongolive.com/ja/post/dev-diaries-introducing-campfire/",
            "date": "2022年7月7日"
        },
        {
            "title": "「Pokémon GO Fest 2022: Berlin」ご参加いただき、ありがとうございました！",
            "link": "https://pokemongolive.com/ja/post/gofest-2022-berlin-recap/",
            "date": "2022年7月6日"
        },
        {
            "title": "『Pokémon GO』の6周年を祝いましょう！",
            "link": "https://pokemongolive.com/ja/post/pgo-anniversary-2022/",
            "date": "2022年7月5日"
        },
        {
            "title": "アニバーサリーイベントと「バトルウィークエンド」で『Pokémon GO』の6周年を祝おう！",
            "link": "https://pokemongolive.com/ja/post/anniversary-event-battle-weekend-2022/",
            "date": "2022年6月29日"
        },
        {
            "title": "「Pokémon GO Fest 2022: Berlin」の「グローバルチャレンジ」と「ウルトラアンロック」についてお知らせします！",
            "link": "https://pokemongolive.com/ja/post/gofest2022-berlin-ultraunlockchallenge/",
            "date": "2022年6月29日"
        },
        {
            "title": "7月の最新情報：7月の「コミュニティ・デイ」、「フリーザー」「サンダー」「ファイヤー」がレイドバトルに再登場、『Pokémon GO』の6周年記念イベントなど！",
            "link": "https://pokemongolive.com/ja/post/july-2022-content-update/",
            "date": "2022年6月28日"
        },
        {
            "title": "2022年7月の「コミュニティ・デイ」：「ムックル」",
            "link": "https://pokemongolive.com/ja/post/communityday-july-2022-starly/",
            "date": "2022年6月27日"
        },
        {
            "title": "世界各都市の「Pokémon GO Fest 2022」リアルイベントでさらなる「ウルトラビースト」が出現！",
            "link": "https://pokemongolive.com/ja/post/ultrabeasts-join-gofest-irl/",
            "date": "2022年6月22日"
        },
        {
            "title": "6月は一部の都市で「コミュニティ・デイ」でリアルの交流を楽しみましょう！",
            "link": "https://pokemongolive.com/ja/post/irl-community-day-june-2022/",
            "date": "2022年6月10日"
        },
        {
            "title": "2022年6月の「コミュニティ・デイ」：「モノズ」",
            "link": "https://pokemongolive.com/ja/post/communityday-june-2022-deino/",
            "date": "2022年6月9日"
        },
        {
            "title": "グローバルイベントの「Pokémon GO Fest 2022」が大盛況のうちに終了しました！",
            "link": "https://pokemongolive.com/ja/post/pokemongofest2022-recap/",
            "date": "2022年6月8日"
        },
        {
            "title": "強化拡張パック「Pokémon GO」の発売を記念して、「ポケモンカードゲームコラボイベント」を開催！",
            "link": "https://pokemongolive.com/ja/post/Pokemon-TCG-Crossover-Event/",
            "date": "2022年6月6日"
        },
        {
            "title": "『Pokémon GO』の「アドベンチャーウィーク2022」：新しいポケモンが登場、ウルトラ級のサプライズも！",
            "link": "https://pokemongolive.com/ja/post/adventure-week-2022/",
            "date": "2022年6月5日"
        },
        {
            "title": "「Pokémon GO Fest 2022」最新情報 - 「ウツロイド」が出現！",
            "link": "https://pokemongolive.com/ja/post/gofest-2022-nihilego/",
            "date": "2022年6月4日"
        },
        {
            "title": "『Pokémon GO』 パートナーリサーチ」のご案内！",
            "link": "https://pokemongolive.com/ja/post/202206partnerresearch-jp/",
            "date": "2022年6月1日"
        },
        {
            "title": "「Pokémon GO Fest 2022」のウルトラアンロックで熱い夏を迎えよう！",
            "link": "https://pokemongolive.com/ja/post/pokemon-go-fest-2022-ultra-unlocks/",
            "date": "2022年5月31日"
        },
        {
            "title": "「シーズンオブGO」",
            "link": "https://pokemongolive.com/ja/post/season-of-go-2022/",
            "date": "2022年5月26日"
        },
        {
            "title": "「GOバトルリーグ」：シーズン11の最新情報",
            "link": "https://pokemongolive.com/ja/post/gobattleleague-season11/",
            "date": "2022年5月26日"
        },
        {
            "title": "6月の最新情報：「Pokémon GO Fest 2022」、「シーズンオブGO」、レイドバトルに「ミュウツー」が登場など、6月も盛りだくさんです！",
            "link": "https://pokemongolive.com/ja/post/june-2022-content-update/",
            "date": "2022年5月26日"
        },
        {
            "title": "「Pokémon GO Fest 2022」の追加情報をお知らせします！",
            "link": "https://pokemongolive.com/ja/post/pokemongofest2022-update/",
            "date": "2022年5月26日"
        },
        {
            "title": "「Pokémon GO Fest 2022: Seattle」のチケットは現在発売中です！",
            "link": "https://pokemongolive.com/ja/post/gofest2022-seattle-tickets/",
            "date": "2022年5月24日"
        },
        {
            "title": "GOバトル・デイ：「ほしのすな」サプライズで「ほしのすな」をたくさん手に入れよう",
            "link": "https://pokemongolive.com/ja/post/go-battle-day-mega-stardust-surprise/",
            "date": "2022年5月23日"
        },
        {
            "title": "次のシーズンで開催される「コミュニティ・デイ」の日程をお知らせします！",
            "link": "https://pokemongolive.com/ja/post/cd-savethedate-s7/",
            "date": "2022年5月23日"
        }
    ]
}